mobilizr_python/__init__.py
mobilizr_python/data/atu_clean.csv
mobilizr_python/data/atu_dirty.csv
mobilizr_python/data/cdc.csv
mobilizr_python/data/food_ids.csv
mobilizr_python/data/slasher.csv
mobilizr_python/data/timeuse_ids.csv
mobilizr_python/data/timeuse_ids_clean.csv
mobilizr_python/datasets/__init__.py
mobilizr_python/datasets/atu_clean.py
mobilizr_python/datasets/atu_dirty.py
mobilizr_python/datasets/cdc.py
mobilizr_python/datasets/food_ids.py
mobilizr_python/datasets/slasher.py
mobilizr_python/datasets/timeuse_ids.py
mobilizr_python/datasets/timeuse_ids_clean.py
mobilizr_python-1.1.dist-info/METADATA
mobilizr_python-1.1.dist-info/WHEEL
mobilizr_python-1.1.dist-info/top_level.txt
mobilizr_python-1.1.dist-info/RECORD
