Metadata-Version: 2.4
Name: mobilizr-python
Version: 1.1
Summary: A library of custom datasets.
Home-page: https://github.com/EmilioD19/mobilizr-python
Author: Emilio Dulay
Author-email: emiliodulay19@g.ucla.edu
Classifier: Programming Language :: Python :: 3
Classifier: License :: OSI Approved :: MIT License
Requires-Dist: pandas
Dynamic: author
Dynamic: author-email
Dynamic: classifier
Dynamic: home-page
Dynamic: requires-dist
Dynamic: summary
